[{"line":1,"elements":[{"line":3,"name":"","description":"","type":"background","keyword":"Background","steps":[{"name":"url baseUrl","result":{"duration":189500,"status":"passed"},"match":{"location":"karate","arguments":[]},"keyword":"*","line":4,"doc_string":{"content_type":"","value":"19:52:39.405 karate.env system property was: uat \n","line":4}},{"name":"path '\/users'","result":{"duration":71799,"status":"passed"},"match":{"location":"karate","arguments":[]},"keyword":"*","line":5},{"name":"def randomEmail = call read('classpath:com\/co\/gorest\/utils\/functionJS\/RandomEmail.js')","result":{"duration":5150000,"status":"passed"},"match":{"location":"karate","arguments":[]},"keyword":"*","line":6},{"name":"def dataRequest = read('classpath:com\/co\/gorest\/users\/request\/usersRequest.json')","result":{"duration":11170101,"status":"passed"},"match":{"location":"karate","arguments":[]},"keyword":"*","line":7},{"name":"def dataResponse = read('classpath:com\/co\/gorest\/users\/response\/responseUsers.json')","result":{"duration":3688200,"status":"passed"},"match":{"location":"karate","arguments":[]},"keyword":"*","line":8}]},{"start_timestamp":"2024-02-07T00:52:39.405Z","line":12,"name":"1 - Validar el listado completo de los usuarios registrados","description":"Dado un  usuario que desea realizar la consulta de todos los usuarios regisrados\r\n    Cuando consume el servicio users\r\n    Entonces se le deben mostrar todos los usuarios registrados","id":"1---validar-el-listado-completo-de-los-usuarios-registrados","type":"scenario","keyword":"Scenario","steps":[{"name":"method get","result":{"duration":1010766300,"status":"passed"},"match":{"location":"karate","arguments":[]},"keyword":"When","line":16,"doc_string":{"content_type":"","value":"19:52:39.433 request:\n1 > GET https:\/\/gorest.co.in\/public\/v2\/users\n1 > Host: gorest.co.in\n1 > Connection: Keep-Alive\n1 > User-Agent: Apache-HttpClient\/4.5.13 (Java\/1.8.0_372)\n1 > Accept-Encoding: gzip,deflate\n\n\n19:52:40.438 response time in milliseconds: 1005\n1 < 200\n1 < Date: Wed, 07 Feb 2024 00:52:40 GMT\n1 < Content-Type: application\/json; charset=utf-8\n1 < Transfer-Encoding: chunked\n1 < Connection: keep-alive\n1 < Cache-Control: max-age=0, private, must-revalidate\n1 < etag: W\/\"7e9d4280ca41aff4b9076baf714defae\"\n1 < referrer-policy: strict-origin-when-cross-origin\n1 < vary: Origin\n1 < x-content-type-options: nosniff\n1 < x-download-options: noopen\n1 < x-frame-options: SAMEORIGIN\n1 < x-links-current: https:\/\/gorest.co.in\/public\/v2\/users?page=1\n1 < x-links-next: https:\/\/gorest.co.in\/public\/v2\/users?page=2\n1 < x-links-previous: \n1 < x-pagination-limit: 10\n1 < x-pagination-page: 1\n1 < x-pagination-pages: 299\n1 < x-pagination-total: 2985\n1 < x-permitted-cross-domain-policies: none\n1 < x-request-id: ee71e1f3-2bcb-44e5-9401-58cb8c38f32c\n1 < x-runtime: 0.051424\n1 < x-xss-protection: 0\n1 < CF-Cache-Status: DYNAMIC\n1 < Report-To: {\"endpoints\":[{\"url\":\"https:\\\/\\\/a.nel.cloudflare.com\\\/report\\\/v3?s=%2FmPigcm6MJ6k%2BiFxAMGDBqaA%2FN9NNVGhY3tlBwqghw0d3RMhAFzWC4ZBRVwLjaHzz3%2Fc%2Buu1hub6HvGqSMVyHR6QNSEkpE71zssnOua8INyLELuhys61nd31RC8%2BNBE%3D\"}],\"group\":\"cf-nel\",\"max_age\":604800}\n1 < NEL: {\"success_fraction\":0,\"report_to\":\"cf-nel\",\"max_age\":604800}\n1 < Server: cloudflare\n1 < CF-RAY: 8517a6c5bd032227-MIA\n1 < alt-svc: h3=\":443\"; ma=86400\n[{\"id\":6180512,\"name\":\"Chandravati Nair\",\"email\":\"chandravati_nair@tremblay.test\",\"gender\":\"female\",\"status\":\"inactive\"},{\"id\":6180511,\"name\":\"Malti Chopra\",\"email\":\"chopra_malti@miller.example\",\"gender\":\"female\",\"status\":\"inactive\"},{\"id\":6180510,\"name\":\"Krishnadas Shah\",\"email\":\"shah_krishnadas@greenholt.test\",\"gender\":\"male\",\"status\":\"active\"},{\"id\":6180509,\"name\":\"Prof. Akshayakeerti Sharma\",\"email\":\"sharma_akshayakeerti_prof@skiles.test\",\"gender\":\"female\",\"status\":\"inactive\"},{\"id\":6180508,\"name\":\"Ms. Anilaabh Tagore\",\"email\":\"tagore_anilaabh_ms@bednar-haley.example\",\"gender\":\"female\",\"status\":\"inactive\"},{\"id\":6180507,\"name\":\"Aanand Bhattathiri\",\"email\":\"aanand_bhattathiri@terry.test\",\"gender\":\"female\",\"status\":\"inactive\"},{\"id\":6180506,\"name\":\"Msgr. Lakshminath Shukla\",\"email\":\"shukla_lakshminath_msgr@boyer-zulauf.example\",\"gender\":\"female\",\"status\":\"active\"},{\"id\":6180505,\"name\":\"Bhoopat Dhawan\",\"email\":\"dhawan_bhoopat@block.example\",\"gender\":\"female\",\"status\":\"active\"},{\"id\":6180504,\"name\":\"Dandapaani Tagore\",\"email\":\"tagore_dandapaani@deckow.test\",\"gender\":\"female\",\"status\":\"active\"},{\"id\":6180503,\"name\":\"Aanand Khan\",\"email\":\"khan_aanand@windler-gibson.example\",\"gender\":\"female\",\"status\":\"inactive\"}]\n\n","line":16}},{"name":"status 200","result":{"duration":5800,"status":"passed"},"match":{"location":"karate","arguments":[]},"keyword":"Then","line":17}],"tags":[{"name":"@Smoke","line":11},{"name":"@users","line":11}]},{"line":3,"name":"","description":"","type":"background","keyword":"Background","steps":[{"name":"url baseUrl","result":{"duration":79299,"status":"passed"},"match":{"location":"karate","arguments":[]},"keyword":"*","line":4,"doc_string":{"content_type":"","value":"19:52:40.443 karate.env system property was: uat \n","line":4}},{"name":"path '\/users'","result":{"duration":67000,"status":"passed"},"match":{"location":"karate","arguments":[]},"keyword":"*","line":5},{"name":"def randomEmail = call read('classpath:com\/co\/gorest\/utils\/functionJS\/RandomEmail.js')","result":{"duration":3361599,"status":"passed"},"match":{"location":"karate","arguments":[]},"keyword":"*","line":6},{"name":"def dataRequest = read('classpath:com\/co\/gorest\/users\/request\/usersRequest.json')","result":{"duration":6406500,"status":"passed"},"match":{"location":"karate","arguments":[]},"keyword":"*","line":7},{"name":"def dataResponse = read('classpath:com\/co\/gorest\/users\/response\/responseUsers.json')","result":{"duration":3186201,"status":"passed"},"match":{"location":"karate","arguments":[]},"keyword":"*","line":8}]},{"start_timestamp":"2024-02-07T00:52:40.443Z","line":20,"name":"2 - Creacion exitosa de un usario","description":"Dado un  usuario que desea registrarse y no existe previamente registrado\r\n  Cuando consume el servicio users enviando la informacion del usuario\r\n  Entonces se debe realizar el registro exitoso del usuario","id":"2---creacion-exitosa-de-un-usario","type":"scenario","keyword":"Scenario","steps":[{"name":"print 'El correo es: ' +randomEmail","result":{"duration":489501,"status":"passed"},"match":{"location":"karate","arguments":[]},"keyword":"*","line":24,"doc_string":{"content_type":"","value":"19:52:40.458 [print] El correo es: slehths0aw@assesment.com \n","line":24}},{"name":"header Authorization = 'Bearer ' + accessToken","result":{"duration":181700,"status":"passed"},"match":{"location":"karate","arguments":[]},"keyword":"Given","line":25},{"name":"request dataRequest.createUser","result":{"duration":87401,"status":"passed"},"match":{"location":"karate","arguments":[]},"keyword":"And","line":26},{"name":"method post","result":{"duration":529842100,"status":"passed"},"match":{"location":"karate","arguments":[]},"keyword":"When","line":27,"doc_string":{"content_type":"","value":"19:52:40.462 request:\n1 > POST https:\/\/gorest.co.in\/public\/v2\/users\n1 > Authorization: Bearer f84b110dfc675dde968296b130fc1bdfe1772367c22d172596a3cb63713afed1\n1 > Content-Type: application\/json; charset=UTF-8\n1 > Content-Length: 93\n1 > Host: gorest.co.in\n1 > Connection: Keep-Alive\n1 > User-Agent: Apache-HttpClient\/4.5.13 (Java\/1.8.0_372)\n1 > Accept-Encoding: gzip,deflate\n{\"name\":\"tester tester\",\"gender\":\"male\",\"email\":\"slehths0aw@assesment.com\",\"status\":\"active\"}\n\n19:52:40.988 response time in milliseconds: 526\n1 < 201\n1 < Date: Wed, 07 Feb 2024 00:52:41 GMT\n1 < Content-Type: application\/json; charset=utf-8\n1 < Content-Length: 106\n1 < Connection: keep-alive\n1 < Cache-Control: max-age=0, private, must-revalidate\n1 < etag: W\/\"8cc6a3279d75292e406b53f5e0da0d60\"\n1 < location: https:\/\/gorest.co.in\/public\/v2\/users\/6182793\n1 < referrer-policy: strict-origin-when-cross-origin\n1 < vary: Origin\n1 < x-content-type-options: nosniff\n1 < x-download-options: noopen\n1 < x-frame-options: SAMEORIGIN\n1 < x-permitted-cross-domain-policies: none\n1 < x-ratelimit-limit: 90\n1 < x-ratelimit-remaining: 88\n1 < x-ratelimit-reset: 1\n1 < x-request-id: c15bffc0-82e5-4345-b414-5d808c63cd73\n1 < x-runtime: 0.095071\n1 < x-xss-protection: 0\n1 < CF-Cache-Status: DYNAMIC\n1 < Report-To: {\"endpoints\":[{\"url\":\"https:\\\/\\\/a.nel.cloudflare.com\\\/report\\\/v3?s=bvDiEDmvc8V3X6lTBA2jXVyxxQ%2BXUj7td12rBI550SE%2FWZ7Ad9mmnUsFCJV6FjVpDWmjGcYgae3CqSE%2Bj%2Bzw7UCCVvL1lzs6XUi6zWSU82q%2BtQllMgo59haeglenNUo%3D\"}],\"group\":\"cf-nel\",\"max_age\":604800}\n1 < NEL: {\"success_fraction\":0,\"report_to\":\"cf-nel\",\"max_age\":604800}\n1 < Server: cloudflare\n1 < CF-RAY: 8517a6cc1a174c2a-MIA\n1 < alt-svc: h3=\":443\"; ma=86400\n{\"id\":6182793,\"name\":\"tester tester\",\"email\":\"slehths0aw@assesment.com\",\"gender\":\"male\",\"status\":\"active\"}\n\n","line":27}},{"name":"status 201","result":{"duration":6700,"status":"passed"},"match":{"location":"karate","arguments":[]},"keyword":"Then","line":28},{"name":"match response == dataResponse.responseUserCreated","result":{"duration":476199,"status":"passed"},"match":{"location":"karate","arguments":[]},"keyword":"And","line":29},{"name":"assert responseTime <= 5000","result":{"duration":109500,"status":"passed"},"match":{"location":"karate","arguments":[]},"keyword":"And","line":30},{"name":"def idUserCreated = response.id","result":{"duration":206399,"status":"passed"},"match":{"location":"karate","arguments":[]},"keyword":"*","line":31},{"name":"def emailUser = response.email","result":{"duration":139000,"status":"passed"},"match":{"location":"karate","arguments":[]},"keyword":"*","line":32},{"name":"print idUserCreated","result":{"duration":509099,"status":"passed"},"match":{"location":"karate","arguments":[]},"keyword":"*","line":33,"doc_string":{"content_type":"","value":"19:52:40.991 [print] 6182793 \n","line":33}}],"tags":[{"name":"@createUser","line":19},{"name":"@Smoke","line":19},{"name":"@users","line":19}]},{"line":3,"name":"","description":"","type":"background","keyword":"Background","steps":[{"name":"url baseUrl","result":{"duration":119700,"status":"passed"},"match":{"location":"karate","arguments":[]},"keyword":"*","line":4,"doc_string":{"content_type":"","value":"19:52:40.995 karate.env system property was: uat \n","line":4}},{"name":"path '\/users'","result":{"duration":79801,"status":"passed"},"match":{"location":"karate","arguments":[]},"keyword":"*","line":5},{"name":"def randomEmail = call read('classpath:com\/co\/gorest\/utils\/functionJS\/RandomEmail.js')","result":{"duration":3594099,"status":"passed"},"match":{"location":"karate","arguments":[]},"keyword":"*","line":6},{"name":"def dataRequest = read('classpath:com\/co\/gorest\/users\/request\/usersRequest.json')","result":{"duration":6325699,"status":"passed"},"match":{"location":"karate","arguments":[]},"keyword":"*","line":7},{"name":"def dataResponse = read('classpath:com\/co\/gorest\/users\/response\/responseUsers.json')","result":{"duration":2097601,"status":"passed"},"match":{"location":"karate","arguments":[]},"keyword":"*","line":8}]},{"start_timestamp":"2024-02-07T00:52:40.994Z","line":36,"name":"3 - Modificacion exitosa de un usario","description":"Dado un usuario que desea modificar el nombre de su informacion previamente registrada\r\n  Cuando consume el servicio users enviando la informacion del usuario par actualizar\r\n  Entonces se debe realizar la actualizacion de la informacion de forma correcta","id":"3---modificacion-exitosa-de-un-usario","type":"scenario","keyword":"Scenario","steps":[{"name":"def createUser = call read('classpath:com\/co\/gorest\/users\/feature\/users.feature@createUser')","result":{"duration":1062384499,"status":"passed"},"match":{"location":"karate","arguments":[]},"keyword":"*","line":40},{"name":"com\/co\/gorest\/users\/feature\/users.feature","result":{"duration":0,"status":"passed"},"match":{"location":"karate","arguments":[]},"keyword":"","line":40},{"name":"url baseUrl","result":{"duration":81800,"status":"passed"},"match":{"location":"karate","arguments":[]},"keyword":"> *","line":4},{"name":"path '\/users'","result":{"duration":45100,"status":"passed"},"match":{"location":"karate","arguments":[]},"keyword":"> *","line":5},{"name":"def randomEmail = call read('classpath:com\/co\/gorest\/utils\/functionJS\/RandomEmail.js')","result":{"duration":3042600,"status":"passed"},"match":{"location":"karate","arguments":[]},"keyword":"> *","line":6},{"name":"def dataRequest = read('classpath:com\/co\/gorest\/users\/request\/usersRequest.json')","result":{"duration":7019100,"status":"passed"},"match":{"location":"karate","arguments":[]},"keyword":"> *","line":7},{"name":"def dataResponse = read('classpath:com\/co\/gorest\/users\/response\/responseUsers.json')","result":{"duration":2356199,"status":"passed"},"match":{"location":"karate","arguments":[]},"keyword":"> *","line":8},{"name":"print 'El correo es: ' +randomEmail","result":{"duration":398400,"status":"passed"},"match":{"location":"karate","arguments":[]},"keyword":"> *","line":24,"doc_string":{"content_type":"","value":"19:52:41.031 [print] El correo es: 3q4rdlsmh7@assesment.com \n","line":24}},{"name":"header Authorization = 'Bearer ' + accessToken","result":{"duration":135200,"status":"passed"},"match":{"location":"karate","arguments":[]},"keyword":"> Given","line":25},{"name":"request dataRequest.createUser","result":{"duration":85801,"status":"passed"},"match":{"location":"karate","arguments":[]},"keyword":"> And","line":26},{"name":"method post","result":{"duration":1036817300,"status":"passed"},"match":{"location":"karate","arguments":[]},"keyword":"> When","line":27,"doc_string":{"content_type":"","value":"19:52:41.033 request:\n1 > POST https:\/\/gorest.co.in\/public\/v2\/users\n1 > Authorization: Bearer f84b110dfc675dde968296b130fc1bdfe1772367c22d172596a3cb63713afed1\n1 > Content-Type: application\/json; charset=UTF-8\n1 > Content-Length: 93\n1 > Host: gorest.co.in\n1 > Connection: Keep-Alive\n1 > User-Agent: Apache-HttpClient\/4.5.13 (Java\/1.8.0_372)\n1 > Accept-Encoding: gzip,deflate\n{\"name\":\"tester tester\",\"gender\":\"male\",\"email\":\"3q4rdlsmh7@assesment.com\",\"status\":\"active\"}\n\n19:52:42.068 response time in milliseconds: 1034\n1 < 201\n1 < Date: Wed, 07 Feb 2024 00:52:42 GMT\n1 < Content-Type: application\/json; charset=utf-8\n1 < Content-Length: 106\n1 < Connection: keep-alive\n1 < Cache-Control: max-age=0, private, must-revalidate\n1 < etag: W\/\"894f166ae4e043f784f40702b26ece30\"\n1 < location: https:\/\/gorest.co.in\/public\/v2\/users\/6182794\n1 < referrer-policy: strict-origin-when-cross-origin\n1 < vary: Origin\n1 < x-content-type-options: nosniff\n1 < x-download-options: noopen\n1 < x-frame-options: SAMEORIGIN\n1 < x-permitted-cross-domain-policies: none\n1 < x-ratelimit-limit: 90\n1 < x-ratelimit-remaining: 89\n1 < x-ratelimit-reset: 1\n1 < x-request-id: bcb75a9a-8b54-4b78-b3f5-171070de120b\n1 < x-runtime: 0.100417\n1 < x-xss-protection: 0\n1 < CF-Cache-Status: DYNAMIC\n1 < Report-To: {\"endpoints\":[{\"url\":\"https:\\\/\\\/a.nel.cloudflare.com\\\/report\\\/v3?s=uXUCGAo2Eh%2BTCP04zeXK8VBqNieu6FFprdHNzxcm7%2BUBSwpTL1Fei%2FiAShSZZ6vPsS3uKs3IMis8yt3BTIBpE96AB0GphTCjGbH9TUbXLBIRhfZbrmrMWQOzU0W%2BIWw%3D\"}],\"group\":\"cf-nel\",\"max_age\":604800}\n1 < NEL: {\"success_fraction\":0,\"report_to\":\"cf-nel\",\"max_age\":604800}\n1 < Server: cloudflare\n1 < CF-RAY: 8517a6cfacb0498a-MIA\n1 < alt-svc: h3=\":443\"; ma=86400\n{\"id\":6182794,\"name\":\"tester tester\",\"email\":\"3q4rdlsmh7@assesment.com\",\"gender\":\"male\",\"status\":\"active\"}\n\n","line":27}},{"name":"status 201","result":{"duration":4899,"status":"passed"},"match":{"location":"karate","arguments":[]},"keyword":"> Then","line":28},{"name":"match response == dataResponse.responseUserCreated","result":{"duration":346799,"status":"passed"},"match":{"location":"karate","arguments":[]},"keyword":"> And","line":29},{"name":"assert responseTime <= 5000","result":{"duration":96000,"status":"passed"},"match":{"location":"karate","arguments":[]},"keyword":"> And","line":30},{"name":"def idUserCreated = response.id","result":{"duration":265801,"status":"passed"},"match":{"location":"karate","arguments":[]},"keyword":"> *","line":31},{"name":"def emailUser = response.email","result":{"duration":161300,"status":"passed"},"match":{"location":"karate","arguments":[]},"keyword":"> *","line":32},{"name":"print idUserCreated","result":{"duration":436300,"status":"passed"},"match":{"location":"karate","arguments":[]},"keyword":"> *","line":33,"doc_string":{"content_type":"","value":"19:52:42.070 [print] 6182794 \n","line":33}},{"name":"def idUserCreated = createUser.idUserCreated","result":{"duration":268601,"status":"passed"},"match":{"location":"karate","arguments":[]},"keyword":"*","line":41},{"name":"path + idUserCreated","result":{"duration":662701,"status":"passed"},"match":{"location":"karate","arguments":[]},"keyword":"Given","line":42},{"name":"header Authorization = 'Bearer ' + accessToken","result":{"duration":164299,"status":"passed"},"match":{"location":"karate","arguments":[]},"keyword":"And","line":43},{"name":"request dataRequest.updateUser","result":{"duration":450500,"status":"passed"},"match":{"location":"karate","arguments":[]},"keyword":"And","line":44},{"name":"method patch","result":{"duration":1040220300,"status":"passed"},"match":{"location":"karate","arguments":[]},"keyword":"When","line":45,"doc_string":{"content_type":"","value":"19:52:42.075 request:\n1 > PATCH https:\/\/gorest.co.in\/public\/v2\/users\/6182794\n1 > Authorization: Bearer f84b110dfc675dde968296b130fc1bdfe1772367c22d172596a3cb63713afed1\n1 > Content-Type: application\/json; charset=UTF-8\n1 > Content-Length: 98\n1 > Host: gorest.co.in\n1 > Connection: Keep-Alive\n1 > User-Agent: Apache-HttpClient\/4.5.13 (Java\/1.8.0_372)\n1 > Accept-Encoding: gzip,deflate\n{\"name\":\"Usuario modificado\",\"gender\":\"male\",\"email\":\"lwljaeb8tg@assesment.com\",\"status\":\"active\"}\n\n19:52:43.112 response time in milliseconds: 1037\n1 < 200\n1 < Date: Wed, 07 Feb 2024 00:52:43 GMT\n1 < Content-Type: application\/json; charset=utf-8\n1 < Transfer-Encoding: chunked\n1 < Connection: keep-alive\n1 < Cache-Control: max-age=0, private, must-revalidate\n1 < etag: W\/\"deb14556724ba27ab9a30a21be395891\"\n1 < referrer-policy: strict-origin-when-cross-origin\n1 < vary: Origin\n1 < x-content-type-options: nosniff\n1 < x-download-options: noopen\n1 < x-frame-options: SAMEORIGIN\n1 < x-permitted-cross-domain-policies: none\n1 < x-ratelimit-limit: 90\n1 < x-ratelimit-remaining: 89\n1 < x-ratelimit-reset: 1\n1 < x-request-id: 683f3251-deda-45c2-a854-ffcebcd3c266\n1 < x-runtime: 0.101443\n1 < x-xss-protection: 0\n1 < CF-Cache-Status: DYNAMIC\n1 < Report-To: {\"endpoints\":[{\"url\":\"https:\\\/\\\/a.nel.cloudflare.com\\\/report\\\/v3?s=RBECaIHLOkePN7U4e5CY70H13AFbT6JlJHSGmcsAvWSXa2wAj1SYvWx31fNfoqesHT9eJmmW8eTvmDBqRZFZa7CLg7JbKOujYiMHJ8sQJdjf6VQpMfW1p25I%2FHX2G%2Fk%3D\"}],\"group\":\"cf-nel\",\"max_age\":604800}\n1 < NEL: {\"success_fraction\":0,\"report_to\":\"cf-nel\",\"max_age\":604800}\n1 < Server: cloudflare\n1 < CF-RAY: 8517a6d62b044c2c-MIA\n1 < alt-svc: h3=\":443\"; ma=86400\n{\"email\":\"lwljaeb8tg@assesment.com\",\"name\":\"Usuario modificado\",\"gender\":\"male\",\"status\":\"active\",\"id\":6182794}\n\n","line":45}},{"name":"status 200","result":{"duration":8800,"status":"passed"},"match":{"location":"karate","arguments":[]},"keyword":"Then","line":46},{"name":"match response == dataResponse.responseUserUpdated","result":{"duration":1003600,"status":"passed"},"match":{"location":"karate","arguments":[]},"keyword":"And","line":47},{"name":"assert responseTime <= 5000","result":{"duration":90099,"status":"passed"},"match":{"location":"karate","arguments":[]},"keyword":"And","line":48}],"tags":[{"name":"@updateUser","line":35},{"name":"@Smoke","line":35},{"name":"@users","line":35}]},{"line":3,"name":"","description":"","type":"background","keyword":"Background","steps":[{"name":"url baseUrl","result":{"duration":110099,"status":"passed"},"match":{"location":"karate","arguments":[]},"keyword":"*","line":4,"doc_string":{"content_type":"","value":"19:52:43.118 karate.env system property was: uat \n","line":4}},{"name":"path '\/users'","result":{"duration":67800,"status":"passed"},"match":{"location":"karate","arguments":[]},"keyword":"*","line":5},{"name":"def randomEmail = call read('classpath:com\/co\/gorest\/utils\/functionJS\/RandomEmail.js')","result":{"duration":3025800,"status":"passed"},"match":{"location":"karate","arguments":[]},"keyword":"*","line":6},{"name":"def dataRequest = read('classpath:com\/co\/gorest\/users\/request\/usersRequest.json')","result":{"duration":11459399,"status":"passed"},"match":{"location":"karate","arguments":[]},"keyword":"*","line":7},{"name":"def dataResponse = read('classpath:com\/co\/gorest\/users\/response\/responseUsers.json')","result":{"duration":2921500,"status":"passed"},"match":{"location":"karate","arguments":[]},"keyword":"*","line":8}]},{"start_timestamp":"2024-02-07T00:52:43.118Z","line":51,"name":"4 - Eliminación exitosa de un usario","description":"Dado un usuario que desea eliminar su informacion previamente registrada\r\n  Cuando consume el servicio users enviando el id\r\n  Entonces se debe realizar la eliminación de la informacion de forma correcta","id":"4---eliminación-exitosa-de-un-usario","type":"scenario","keyword":"Scenario","steps":[{"name":"def createUser = call read('classpath:com\/co\/gorest\/users\/feature\/users.feature@createUser')","result":{"duration":1374125601,"status":"passed"},"match":{"location":"karate","arguments":[]},"keyword":"*","line":55},{"name":"com\/co\/gorest\/users\/feature\/users.feature","result":{"duration":0,"status":"passed"},"match":{"location":"karate","arguments":[]},"keyword":"","line":55},{"name":"url baseUrl","result":{"duration":136300,"status":"passed"},"match":{"location":"karate","arguments":[]},"keyword":"> *","line":4},{"name":"path '\/users'","result":{"duration":50600,"status":"passed"},"match":{"location":"karate","arguments":[]},"keyword":"> *","line":5},{"name":"def randomEmail = call read('classpath:com\/co\/gorest\/utils\/functionJS\/RandomEmail.js')","result":{"duration":6030601,"status":"passed"},"match":{"location":"karate","arguments":[]},"keyword":"> *","line":6},{"name":"def dataRequest = read('classpath:com\/co\/gorest\/users\/request\/usersRequest.json')","result":{"duration":10034700,"status":"passed"},"match":{"location":"karate","arguments":[]},"keyword":"> *","line":7},{"name":"def dataResponse = read('classpath:com\/co\/gorest\/users\/response\/responseUsers.json')","result":{"duration":2595000,"status":"passed"},"match":{"location":"karate","arguments":[]},"keyword":"> *","line":8},{"name":"print 'El correo es: ' +randomEmail","result":{"duration":1517100,"status":"passed"},"match":{"location":"karate","arguments":[]},"keyword":"> *","line":24,"doc_string":{"content_type":"","value":"19:52:43.170 [print] El correo es: ibnfdyy8tl@assesment.com \n","line":24}},{"name":"header Authorization = 'Bearer ' + accessToken","result":{"duration":280500,"status":"passed"},"match":{"location":"karate","arguments":[]},"keyword":"> Given","line":25},{"name":"request dataRequest.createUser","result":{"duration":229200,"status":"passed"},"match":{"location":"karate","arguments":[]},"keyword":"> And","line":26},{"name":"method post","result":{"duration":1338455200,"status":"passed"},"match":{"location":"karate","arguments":[]},"keyword":"> When","line":27,"doc_string":{"content_type":"","value":"19:52:43.173 request:\n1 > POST https:\/\/gorest.co.in\/public\/v2\/users\n1 > Authorization: Bearer f84b110dfc675dde968296b130fc1bdfe1772367c22d172596a3cb63713afed1\n1 > Content-Type: application\/json; charset=UTF-8\n1 > Content-Length: 93\n1 > Host: gorest.co.in\n1 > Connection: Keep-Alive\n1 > User-Agent: Apache-HttpClient\/4.5.13 (Java\/1.8.0_372)\n1 > Accept-Encoding: gzip,deflate\n{\"name\":\"tester tester\",\"gender\":\"male\",\"email\":\"ibnfdyy8tl@assesment.com\",\"status\":\"active\"}\n\n19:52:44.509 response time in milliseconds: 1335\n1 < 201\n1 < Date: Wed, 07 Feb 2024 00:52:44 GMT\n1 < Content-Type: application\/json; charset=utf-8\n1 < Content-Length: 106\n1 < Connection: keep-alive\n1 < Cache-Control: max-age=0, private, must-revalidate\n1 < etag: W\/\"d194761a8d1e206500efeeefce8b84ed\"\n1 < location: https:\/\/gorest.co.in\/public\/v2\/users\/6182796\n1 < referrer-policy: strict-origin-when-cross-origin\n1 < vary: Origin\n1 < x-content-type-options: nosniff\n1 < x-download-options: noopen\n1 < x-frame-options: SAMEORIGIN\n1 < x-permitted-cross-domain-policies: none\n1 < x-ratelimit-limit: 90\n1 < x-ratelimit-remaining: 89\n1 < x-ratelimit-reset: 1\n1 < x-request-id: cd40af00-e568-491e-aaed-df0cac9523ea\n1 < x-runtime: 0.143617\n1 < x-xss-protection: 0\n1 < CF-Cache-Status: DYNAMIC\n1 < Report-To: {\"endpoints\":[{\"url\":\"https:\\\/\\\/a.nel.cloudflare.com\\\/report\\\/v3?s=JqxK4d16bOkRmFfvqLorQjwzoPx4uQuzmFtsfilDUDS8ujz6BjHY%2FiLFnIEaGrrODGSHzAQNwBOWKPH7EzGBDttw9eYhaENoyg%2BMrKppnVkglZYFg2pVFC1jqKr57as%3D\"}],\"group\":\"cf-nel\",\"max_age\":604800}\n1 < NEL: {\"success_fraction\":0,\"report_to\":\"cf-nel\",\"max_age\":604800}\n1 < Server: cloudflare\n1 < CF-RAY: 8517a6de79315c70-MIA\n1 < alt-svc: h3=\":443\"; ma=86400\n{\"id\":6182796,\"name\":\"tester tester\",\"email\":\"ibnfdyy8tl@assesment.com\",\"gender\":\"male\",\"status\":\"active\"}\n\n","line":27}},{"name":"status 201","result":{"duration":8000,"status":"passed"},"match":{"location":"karate","arguments":[]},"keyword":"> Then","line":28},{"name":"match response == dataResponse.responseUserCreated","result":{"duration":481100,"status":"passed"},"match":{"location":"karate","arguments":[]},"keyword":"> And","line":29},{"name":"assert responseTime <= 5000","result":{"duration":192299,"status":"passed"},"match":{"location":"karate","arguments":[]},"keyword":"> And","line":30},{"name":"def idUserCreated = response.id","result":{"duration":335600,"status":"passed"},"match":{"location":"karate","arguments":[]},"keyword":"> *","line":31},{"name":"def emailUser = response.email","result":{"duration":178900,"status":"passed"},"match":{"location":"karate","arguments":[]},"keyword":"> *","line":32},{"name":"print idUserCreated","result":{"duration":762200,"status":"passed"},"match":{"location":"karate","arguments":[]},"keyword":"> *","line":33,"doc_string":{"content_type":"","value":"19:52:44.512 [print] 6182796 \n","line":33}},{"name":"def idUserCreated = createUser.idUserCreated","result":{"duration":270299,"status":"passed"},"match":{"location":"karate","arguments":[]},"keyword":"*","line":56},{"name":"path + idUserCreated","result":{"duration":68899,"status":"passed"},"match":{"location":"karate","arguments":[]},"keyword":"Given","line":57},{"name":"header Authorization = 'Bearer ' + accessToken","result":{"duration":216600,"status":"passed"},"match":{"location":"karate","arguments":[]},"keyword":"And","line":58},{"name":"method delete","result":{"duration":1294846500,"status":"passed"},"match":{"location":"karate","arguments":[]},"keyword":"When","line":59,"doc_string":{"content_type":"","value":"19:52:44.516 request:\n1 > DELETE https:\/\/gorest.co.in\/public\/v2\/users\/6182796\n1 > Authorization: Bearer f84b110dfc675dde968296b130fc1bdfe1772367c22d172596a3cb63713afed1\n1 > Host: gorest.co.in\n1 > Connection: Keep-Alive\n1 > User-Agent: Apache-HttpClient\/4.5.13 (Java\/1.8.0_372)\n1 > Accept-Encoding: gzip,deflate\n\n\n19:52:45.808 response time in milliseconds: 1291\n1 < 204\n1 < Date: Wed, 07 Feb 2024 00:52:46 GMT\n1 < Connection: keep-alive\n1 < Cache-Control: no-cache\n1 < referrer-policy: strict-origin-when-cross-origin\n1 < vary: Origin\n1 < x-content-type-options: nosniff\n1 < x-download-options: noopen\n1 < x-frame-options: SAMEORIGIN\n1 < x-permitted-cross-domain-policies: none\n1 < x-ratelimit-limit: 90\n1 < x-ratelimit-remaining: 89\n1 < x-ratelimit-reset: 1\n1 < x-request-id: d5f73c16-cdfd-4a79-868c-e6fb056f0d0f\n1 < x-runtime: 0.095354\n1 < x-xss-protection: 0\n1 < CF-Cache-Status: DYNAMIC\n1 < Report-To: {\"endpoints\":[{\"url\":\"https:\\\/\\\/a.nel.cloudflare.com\\\/report\\\/v3?s=SOWEJ4B4gUQEg0mB2EnSSAiTEmxLR1g7HQS1MotGQsT8bR%2F7lxk8TuIlcuU%2BHrJrM4bCZGi1RYqSXoXcqaaugw1B28I0Oz97e8ha6JuI%2FEOPE%2F3l1Abr9EKydFmM0VU%3D\"}],\"group\":\"cf-nel\",\"max_age\":604800}\n1 < NEL: {\"success_fraction\":0,\"report_to\":\"cf-nel\",\"max_age\":604800}\n1 < Server: cloudflare\n1 < CF-RAY: 8517a6e6fbb26da7-MIA\n1 < alt-svc: h3=\":443\"; ma=86400\n\n\n","line":59}},{"name":"status 204","result":{"duration":6501,"status":"passed"},"match":{"location":"karate","arguments":[]},"keyword":"Then","line":60},{"name":"assert responseTime <= 5000","result":{"duration":152900,"status":"passed"},"match":{"location":"karate","arguments":[]},"keyword":"And","line":61}],"tags":[{"name":"@deleteUser","line":50},{"name":"@Smoke","line":50},{"name":"@users","line":50}]},{"line":3,"name":"","description":"","type":"background","keyword":"Background","steps":[{"name":"url baseUrl","result":{"duration":64301,"status":"passed"},"match":{"location":"karate","arguments":[]},"keyword":"*","line":4,"doc_string":{"content_type":"","value":"19:52:45.813 karate.env system property was: uat \n","line":4}},{"name":"path '\/users'","result":{"duration":46500,"status":"passed"},"match":{"location":"karate","arguments":[]},"keyword":"*","line":5},{"name":"def randomEmail = call read('classpath:com\/co\/gorest\/utils\/functionJS\/RandomEmail.js')","result":{"duration":4068600,"status":"passed"},"match":{"location":"karate","arguments":[]},"keyword":"*","line":6},{"name":"def dataRequest = read('classpath:com\/co\/gorest\/users\/request\/usersRequest.json')","result":{"duration":8397100,"status":"passed"},"match":{"location":"karate","arguments":[]},"keyword":"*","line":7},{"name":"def dataResponse = read('classpath:com\/co\/gorest\/users\/response\/responseUsers.json')","result":{"duration":2539599,"status":"passed"},"match":{"location":"karate","arguments":[]},"keyword":"*","line":8}]},{"start_timestamp":"2024-02-07T00:52:45.813Z","line":64,"name":"5 - Consulta de un usuario previamente creado","description":"Dado un  usuario que desea consultar la información de un usuario creado previamente\r\n  Cuando consume el servicio users enviando el id del usuario\r\n  Entonces se debe devolver la información del usuario correspondiente","id":"5---consulta-de-un-usuario-previamente-creado","type":"scenario","keyword":"Scenario","steps":[{"name":"def createUser = call read('classpath:com\/co\/gorest\/users\/feature\/users.feature@createUser')","result":{"duration":758040200,"status":"passed"},"match":{"location":"karate","arguments":[]},"keyword":"*","line":68},{"name":"com\/co\/gorest\/users\/feature\/users.feature","result":{"duration":0,"status":"passed"},"match":{"location":"karate","arguments":[]},"keyword":"","line":68},{"name":"url baseUrl","result":{"duration":98700,"status":"passed"},"match":{"location":"karate","arguments":[]},"keyword":"> *","line":4},{"name":"path '\/users'","result":{"duration":51299,"status":"passed"},"match":{"location":"karate","arguments":[]},"keyword":"> *","line":5},{"name":"def randomEmail = call read('classpath:com\/co\/gorest\/utils\/functionJS\/RandomEmail.js')","result":{"duration":3800100,"status":"passed"},"match":{"location":"karate","arguments":[]},"keyword":"> *","line":6},{"name":"def dataRequest = read('classpath:com\/co\/gorest\/users\/request\/usersRequest.json')","result":{"duration":7987201,"status":"passed"},"match":{"location":"karate","arguments":[]},"keyword":"> *","line":7},{"name":"def dataResponse = read('classpath:com\/co\/gorest\/users\/response\/responseUsers.json')","result":{"duration":2384499,"status":"passed"},"match":{"location":"karate","arguments":[]},"keyword":"> *","line":8},{"name":"print 'El correo es: ' +randomEmail","result":{"duration":481601,"status":"passed"},"match":{"location":"karate","arguments":[]},"keyword":"> *","line":24,"doc_string":{"content_type":"","value":"19:52:45.854 [print] El correo es: yiauztmtz4@assesment.com \n","line":24}},{"name":"header Authorization = 'Bearer ' + accessToken","result":{"duration":107600,"status":"passed"},"match":{"location":"karate","arguments":[]},"keyword":"> Given","line":25},{"name":"request dataRequest.createUser","result":{"duration":57300,"status":"passed"},"match":{"location":"karate","arguments":[]},"keyword":"> And","line":26},{"name":"method post","result":{"duration":730981699,"status":"passed"},"match":{"location":"karate","arguments":[]},"keyword":"> When","line":27,"doc_string":{"content_type":"","value":"19:52:45.856 request:\n1 > POST https:\/\/gorest.co.in\/public\/v2\/users\n1 > Authorization: Bearer f84b110dfc675dde968296b130fc1bdfe1772367c22d172596a3cb63713afed1\n1 > Content-Type: application\/json; charset=UTF-8\n1 > Content-Length: 93\n1 > Host: gorest.co.in\n1 > Connection: Keep-Alive\n1 > User-Agent: Apache-HttpClient\/4.5.13 (Java\/1.8.0_372)\n1 > Accept-Encoding: gzip,deflate\n{\"name\":\"tester tester\",\"gender\":\"male\",\"email\":\"yiauztmtz4@assesment.com\",\"status\":\"active\"}\n\n19:52:46.585 response time in milliseconds: 728\n1 < 201\n1 < Date: Wed, 07 Feb 2024 00:52:46 GMT\n1 < Content-Type: application\/json; charset=utf-8\n1 < Content-Length: 106\n1 < Connection: keep-alive\n1 < Cache-Control: max-age=0, private, must-revalidate\n1 < etag: W\/\"5d31d9ca110e70443de8dfe825e1aac9\"\n1 < location: https:\/\/gorest.co.in\/public\/v2\/users\/6182797\n1 < referrer-policy: strict-origin-when-cross-origin\n1 < vary: Origin\n1 < x-content-type-options: nosniff\n1 < x-download-options: noopen\n1 < x-frame-options: SAMEORIGIN\n1 < x-permitted-cross-domain-policies: none\n1 < x-ratelimit-limit: 90\n1 < x-ratelimit-remaining: 89\n1 < x-ratelimit-reset: 1\n1 < x-request-id: 07da5879-dd1b-4344-a99e-3b8ee3c660f5\n1 < x-runtime: 0.090870\n1 < x-xss-protection: 0\n1 < CF-Cache-Status: DYNAMIC\n1 < Report-To: {\"endpoints\":[{\"url\":\"https:\\\/\\\/a.nel.cloudflare.com\\\/report\\\/v3?s=HzqOU7h%2BfOOXGon5CEn99wpz6QfTEUgl1B6Tf%2BJTpcOGfS8TLnqEtC%2BDx56iVVU2CZqugG8E%2FtQgQH0QkPumiwGJwwfPHLTptNIyjGrLW%2BzzDTmhWF%2FiTW9N7WwmHK4%3D\"}],\"group\":\"cf-nel\",\"max_age\":604800}\n1 < NEL: {\"success_fraction\":0,\"report_to\":\"cf-nel\",\"max_age\":604800}\n1 < Server: cloudflare\n1 < CF-RAY: 8517a6ef2b754c2a-MIA\n1 < alt-svc: h3=\":443\"; ma=86400\n{\"id\":6182797,\"name\":\"tester tester\",\"email\":\"yiauztmtz4@assesment.com\",\"gender\":\"male\",\"status\":\"active\"}\n\n","line":27}},{"name":"status 201","result":{"duration":4201,"status":"passed"},"match":{"location":"karate","arguments":[]},"keyword":"> Then","line":28},{"name":"match response == dataResponse.responseUserCreated","result":{"duration":291100,"status":"passed"},"match":{"location":"karate","arguments":[]},"keyword":"> And","line":29},{"name":"assert responseTime <= 5000","result":{"duration":77100,"status":"passed"},"match":{"location":"karate","arguments":[]},"keyword":"> And","line":30},{"name":"def idUserCreated = response.id","result":{"duration":133400,"status":"passed"},"match":{"location":"karate","arguments":[]},"keyword":"> *","line":31},{"name":"def emailUser = response.email","result":{"duration":60300,"status":"passed"},"match":{"location":"karate","arguments":[]},"keyword":"> *","line":32},{"name":"print idUserCreated","result":{"duration":428100,"status":"passed"},"match":{"location":"karate","arguments":[]},"keyword":"> *","line":33,"doc_string":{"content_type":"","value":"19:52:46.587 [print] 6182797 \n","line":33}},{"name":"def idUserCreated = createUser.response.id","result":{"duration":990000,"status":"passed"},"match":{"location":"karate","arguments":[]},"keyword":"*","line":69},{"name":"path + idUserCreated","result":{"duration":126600,"status":"passed"},"match":{"location":"karate","arguments":[]},"keyword":"Given","line":70},{"name":"header Authorization = 'Bearer ' + accessToken","result":{"duration":104601,"status":"passed"},"match":{"location":"karate","arguments":[]},"keyword":"And","line":71},{"name":"method get","result":{"duration":1691823900,"status":"passed"},"match":{"location":"karate","arguments":[]},"keyword":"When","line":72,"doc_string":{"content_type":"","value":"19:52:46.591 request:\n1 > GET https:\/\/gorest.co.in\/public\/v2\/users\/6182797\n1 > Authorization: Bearer f84b110dfc675dde968296b130fc1bdfe1772367c22d172596a3cb63713afed1\n1 > Host: gorest.co.in\n1 > Connection: Keep-Alive\n1 > User-Agent: Apache-HttpClient\/4.5.13 (Java\/1.8.0_372)\n1 > Accept-Encoding: gzip,deflate\n\n\n19:52:48.281 response time in milliseconds: 1689\n1 < 200\n1 < Date: Wed, 07 Feb 2024 00:52:48 GMT\n1 < Content-Type: application\/json; charset=utf-8\n1 < Transfer-Encoding: chunked\n1 < Connection: keep-alive\n1 < Cache-Control: max-age=0, private, must-revalidate\n1 < etag: W\/\"5d31d9ca110e70443de8dfe825e1aac9\"\n1 < referrer-policy: strict-origin-when-cross-origin\n1 < vary: Origin\n1 < x-content-type-options: nosniff\n1 < x-download-options: noopen\n1 < x-frame-options: SAMEORIGIN\n1 < x-permitted-cross-domain-policies: none\n1 < x-ratelimit-limit: 90\n1 < x-ratelimit-remaining: 89\n1 < x-ratelimit-reset: 1\n1 < x-request-id: 2ff0fe82-bf25-4bd1-8947-c2917471d8f6\n1 < x-runtime: 0.046963\n1 < x-xss-protection: 0\n1 < CF-Cache-Status: DYNAMIC\n1 < Report-To: {\"endpoints\":[{\"url\":\"https:\\\/\\\/a.nel.cloudflare.com\\\/report\\\/v3?s=tNfYW1Cyw8QmZ2nq%2BoveG1lLpioF5EaF%2BGztaLvoXwJOmFn7dgEh0soouPn8977Fnj%2FRKDBE%2FuJJ6Pws4xVhS7qtD%2FTWtc%2FxeL35MP5KyWiIB%2B5bb1eenhBFcdrTPEw%3D\"}],\"group\":\"cf-nel\",\"max_age\":604800}\n1 < NEL: {\"success_fraction\":0,\"report_to\":\"cf-nel\",\"max_age\":604800}\n1 < Server: cloudflare\n1 < CF-RAY: 8517a6f699e174c8-MIA\n1 < alt-svc: h3=\":443\"; ma=86400\n{\"id\":6182797,\"name\":\"tester tester\",\"email\":\"yiauztmtz4@assesment.com\",\"gender\":\"male\",\"status\":\"active\"}\n\n","line":72}},{"name":"status 200","result":{"duration":5201,"status":"passed"},"match":{"location":"karate","arguments":[]},"keyword":"Then","line":73},{"name":"assert responseTime <= 5000","result":{"duration":90200,"status":"passed"},"match":{"location":"karate","arguments":[]},"keyword":"And","line":74},{"name":"match response.id == createUser.response.id","result":{"duration":426000,"status":"passed"},"match":{"location":"karate","arguments":[]},"keyword":"And","line":75},{"name":"match response.name == createUser.response.name","result":{"duration":533799,"status":"passed"},"match":{"location":"karate","arguments":[]},"keyword":"And","line":76},{"name":"match response.email == createUser.response.email","result":{"duration":529601,"status":"passed"},"match":{"location":"karate","arguments":[]},"keyword":"And","line":77},{"name":"match response.gender == createUser.response.gender","result":{"duration":642001,"status":"passed"},"match":{"location":"karate","arguments":[]},"keyword":"And","line":78},{"name":"match response.status == createUser.response.status","result":{"duration":841700,"status":"passed"},"match":{"location":"karate","arguments":[]},"keyword":"And","line":79}],"tags":[{"name":"@consultUser","line":63},{"name":"@Smoke","line":63},{"name":"@users","line":63}]},{"line":3,"name":"","description":"","type":"background","keyword":"Background","steps":[{"name":"url baseUrl","result":{"duration":84799,"status":"passed"},"match":{"location":"karate","arguments":[]},"keyword":"*","line":4,"doc_string":{"content_type":"","value":"19:52:48.292 karate.env system property was: uat \n","line":4}},{"name":"path '\/users'","result":{"duration":55900,"status":"passed"},"match":{"location":"karate","arguments":[]},"keyword":"*","line":5},{"name":"def randomEmail = call read('classpath:com\/co\/gorest\/utils\/functionJS\/RandomEmail.js')","result":{"duration":4490000,"status":"passed"},"match":{"location":"karate","arguments":[]},"keyword":"*","line":6},{"name":"def dataRequest = read('classpath:com\/co\/gorest\/users\/request\/usersRequest.json')","result":{"duration":8549599,"status":"passed"},"match":{"location":"karate","arguments":[]},"keyword":"*","line":7},{"name":"def dataResponse = read('classpath:com\/co\/gorest\/users\/response\/responseUsers.json')","result":{"duration":3634400,"status":"passed"},"match":{"location":"karate","arguments":[]},"keyword":"*","line":8}]},{"start_timestamp":"2024-02-07T00:52:48.291Z","line":82,"name":"6 - Consulta de un usuario no registrado","description":"Dado un  usuario que desea consultar la información de un usuario no registrado\r\n  Cuando consume el servicio users enviando un id el cual no se encuentra registrado\r\n  Entonces no se debe responder informacion de ningun usuario","id":"6---consulta-de-un-usuario-no-registrado","type":"scenario","keyword":"Scenario","steps":[{"name":"path + '1010'","result":{"duration":253000,"status":"passed"},"match":{"location":"karate","arguments":[]},"keyword":"Given","line":86},{"name":"method get","result":{"duration":4156358900,"status":"passed"},"match":{"location":"karate","arguments":[]},"keyword":"When","line":87,"doc_string":{"content_type":"","value":"19:52:48.313 request:\n1 > GET https:\/\/gorest.co.in\/public\/v2\/users\/1010\n1 > Host: gorest.co.in\n1 > Connection: Keep-Alive\n1 > User-Agent: Apache-HttpClient\/4.5.13 (Java\/1.8.0_372)\n1 > Accept-Encoding: gzip,deflate\n\n\n19:52:52.466 response time in milliseconds: 4153\n1 < 404\n1 < Date: Wed, 07 Feb 2024 00:52:52 GMT\n1 < Content-Type: application\/json; charset=utf-8\n1 < Content-Length: 32\n1 < Connection: keep-alive\n1 < Cache-Control: no-cache\n1 < referrer-policy: strict-origin-when-cross-origin\n1 < vary: Origin\n1 < x-content-type-options: nosniff\n1 < x-download-options: noopen\n1 < x-frame-options: SAMEORIGIN\n1 < x-permitted-cross-domain-policies: none\n1 < x-request-id: d00fcb73-3b91-4ab7-ab38-04342ccccdd9\n1 < x-runtime: 0.014940\n1 < x-xss-protection: 0\n1 < CF-Cache-Status: DYNAMIC\n1 < Report-To: {\"endpoints\":[{\"url\":\"https:\\\/\\\/a.nel.cloudflare.com\\\/report\\\/v3?s=RsIGWHbitaNOOcm0NjtuQM5RWZhpTzloYqtNZDqIOiwRQFrWYn1M3wwrg%2FHS01UG8lZ2GwKRBJgix44Etkp%2B%2BQj8%2BB%2FglBxl5XvEgI9yfur7bpsxBr7HR9L1q7gN4QA%3D\"}],\"group\":\"cf-nel\",\"max_age\":604800}\n1 < NEL: {\"success_fraction\":0,\"report_to\":\"cf-nel\",\"max_age\":604800}\n1 < Server: cloudflare\n1 < CF-RAY: 8517a7113b53741c-MIA\n1 < alt-svc: h3=\":443\"; ma=86400\n{\"message\":\"Resource not found\"}\n\n","line":87}},{"name":"status 404","result":{"duration":9000,"status":"passed"},"match":{"location":"karate","arguments":[]},"keyword":"Then","line":88},{"name":"assert responseTime <= 5000","result":{"duration":163599,"status":"passed"},"match":{"location":"karate","arguments":[]},"keyword":"And","line":89},{"name":"match response == dataResponse.ResponseUserNotRegister","result":{"duration":1282501,"status":"passed"},"match":{"location":"karate","arguments":[]},"keyword":"And","line":90}],"tags":[{"name":"@consultUserNoRegister","line":81},{"name":"@Smoke","line":81},{"name":"@users","line":81}]},{"line":3,"name":"","description":"","type":"background","keyword":"Background","steps":[{"name":"url baseUrl","result":{"duration":182600,"status":"passed"},"match":{"location":"karate","arguments":[]},"keyword":"*","line":4,"doc_string":{"content_type":"","value":"19:52:52.477 karate.env system property was: uat \n","line":4}},{"name":"path '\/users'","result":{"duration":102700,"status":"passed"},"match":{"location":"karate","arguments":[]},"keyword":"*","line":5},{"name":"def randomEmail = call read('classpath:com\/co\/gorest\/utils\/functionJS\/RandomEmail.js')","result":{"duration":4493300,"status":"passed"},"match":{"location":"karate","arguments":[]},"keyword":"*","line":6},{"name":"def dataRequest = read('classpath:com\/co\/gorest\/users\/request\/usersRequest.json')","result":{"duration":7488301,"status":"passed"},"match":{"location":"karate","arguments":[]},"keyword":"*","line":7},{"name":"def dataResponse = read('classpath:com\/co\/gorest\/users\/response\/responseUsers.json')","result":{"duration":2505701,"status":"passed"},"match":{"location":"karate","arguments":[]},"keyword":"*","line":8}]},{"start_timestamp":"2024-02-07T00:52:52.476Z","line":93,"name":"7 - Creacion de un usuario con email repetido","description":"Dado un  usuario que desea registrar un email previamente registrdo\r\n  Cuando consume el servicio users enviando un email  el cual ya  encuentra registrado\r\n  Entonces no se debe responder con error","id":"7---creacion-de-un-usuario-con-email-repetido","type":"scenario","keyword":"Scenario","steps":[{"name":"header Authorization = 'Bearer ' + accessToken","result":{"duration":92300,"status":"passed"},"match":{"location":"karate","arguments":[]},"keyword":"Given","line":97},{"name":"request dataRequest.createExistUser","result":{"duration":535600,"status":"passed"},"match":{"location":"karate","arguments":[]},"keyword":"And","line":98},{"name":"retry until responseStatus == 422","result":{"duration":31600,"status":"passed"},"match":{"location":"karate","arguments":[]},"keyword":"And","line":99},{"name":"method post","result":{"duration":1248682299,"status":"passed"},"match":{"location":"karate","arguments":[]},"keyword":"When","line":100,"doc_string":{"content_type":"","value":"19:52:52.498 request:\n1 > POST https:\/\/gorest.co.in\/public\/v2\/users\n1 > Authorization: Bearer f84b110dfc675dde968296b130fc1bdfe1772367c22d172596a3cb63713afed1\n1 > Content-Type: application\/json; charset=UTF-8\n1 > Content-Length: 82\n1 > Host: gorest.co.in\n1 > Connection: Keep-Alive\n1 > User-Agent: Apache-HttpClient\/4.5.13 (Java\/1.8.0_372)\n1 > Accept-Encoding: gzip,deflate\n{\"name\":\"tester tester\",\"gender\":\"male\",\"email\":\"test@test.com\",\"status\":\"active\"}\n\n19:52:53.738 response time in milliseconds: 1240\n1 < 422\n1 < Date: Wed, 07 Feb 2024 00:52:54 GMT\n1 < Content-Type: application\/json; charset=utf-8\n1 < Content-Length: 54\n1 < Connection: keep-alive\n1 < Cache-Control: no-cache\n1 < referrer-policy: strict-origin-when-cross-origin\n1 < vary: Origin\n1 < x-content-type-options: nosniff\n1 < x-download-options: noopen\n1 < x-frame-options: SAMEORIGIN\n1 < x-permitted-cross-domain-policies: none\n1 < x-ratelimit-limit: 90\n1 < x-ratelimit-remaining: 89\n1 < x-ratelimit-reset: 1\n1 < x-request-id: c3386700-782c-404a-b2f7-7206a228e08b\n1 < x-runtime: 0.075795\n1 < x-xss-protection: 0\n1 < CF-Cache-Status: DYNAMIC\n1 < Report-To: {\"endpoints\":[{\"url\":\"https:\\\/\\\/a.nel.cloudflare.com\\\/report\\\/v3?s=EzR5wnD2bsxi8kMW6uHEO%2B4FSTiS9W%2FnJ4a%2BnPAQDBHRlUmXX1j8jJQygRERbSDY8i9M7Y%2FraYhIyPLhlqr6pacD2rsppa25bBqMSt8HXkc%2FzvZqSBAN6ZuW%2BcAa3sc%3D\"}],\"group\":\"cf-nel\",\"max_age\":604800}\n1 < NEL: {\"success_fraction\":0,\"report_to\":\"cf-nel\",\"max_age\":604800}\n1 < Server: cloudflare\n1 < CF-RAY: 8517a71899a225a7-MIA\n1 < alt-svc: h3=\":443\"; ma=86400\n[{\"field\":\"email\",\"message\":\"has already been taken\"}]\n\n","line":100}},{"name":"status 422","result":{"duration":4401,"status":"passed"},"match":{"location":"karate","arguments":[]},"keyword":"Then","line":101},{"name":"assert responseTime <= 5000","result":{"duration":63299,"status":"passed"},"match":{"location":"karate","arguments":[]},"keyword":"And","line":102},{"name":"match response == dataResponse.responseEmailExists","result":{"duration":554501,"status":"passed"},"match":{"location":"karate","arguments":[]},"keyword":"And","line":103}],"tags":[{"name":"@EmailExists","line":92},{"name":"@Smoke","line":92},{"name":"@users","line":92}]}],"name":"com\/co\/gorest\/users\/feature\/users.feature","description":"Servicio correspondiente a la gestion de los usuarios","id":"servicio-correspondiente-a-la-gestion-de-los-usuarios","keyword":"Feature","uri":"com\/co\/gorest\/users\/feature\/users.feature"}]